{"stat.chestOpened":2,"stat.walkOneCm":7434,"stat.craftItem.minecraft.sign":3,"stat.craftItem.minecraft.planks":60,"stat.leaveGame":2,"stat.mineBlock.minecraft.leaves2":6,"stat.mineBlock.minecraft.log2":15,"stat.mineBlock.minecraft.crafting_table":1,"stat.useItem.minecraft.diamond_axe":20,"stat.craftItem.minecraft.crafting_table":1,"stat.flyOneCm":100887,"stat.drop":2,"stat.jump":43,"stat.playOneMinute":13817,"stat.damageDealt":75,"stat.crouchOneCm":685,"stat.timeSinceDeath":13817,"stat.useItem.minecraft.dirt":1,"stat.sprintOneCm":2364,"stat.mineBlock.minecraft.dirt":121,"stat.useItem.minecraft.crafting_table":1,"stat.useItem.minecraft.sign":5,"achievement.exploreAllBiomes":{"value":0,"progress":["Forest","River","Plains","Desert","Savanna"]},"stat.craftItem.minecraft.stick":4,"stat.craftingTableInteraction":1}